tlnr/__init__.py
tlnr/cli.py
tlnr/core.py
tlnr/daemon.py
tlnr/diagnostics.py
tlnr/installer.py
tlnr/licensing.py
tlnr/local_llm.py
tlnr/openai_manager.py
tlnr/zsh_integration.zsh
tlnr/data/commands.json
tlnr-0.1.71.dist-info/licenses/LICENSE
tlnr-0.1.71.dist-info/METADATA
tlnr-0.1.71.dist-info/WHEEL
tlnr-0.1.71.dist-info/entry_points.txt
tlnr-0.1.71.dist-info/top_level.txt
tlnr-0.1.71.dist-info/RECORD
