Metadata-Version: 2.4
Name: tlnr
Version: 0.1.71
Summary: TLNR (Too Long; No Need To Read) - Real-time terminal command education for Zsh
Home-page: https://github.com/jatinmayekar/tlnr
Author: Jatin Mayekar
Author-email: Jatin Mayekar <jatin@tlnr.dev>
License: AGPL-3.0
Project-URL: Homepage, https://github.com/jatinmayekar/tlnr
Classifier: Development Status :: 4 - Beta
Classifier: Intended Audience :: Developers
Classifier: Programming Language :: Python :: 3
Classifier: Programming Language :: Python :: 3.7
Classifier: Programming Language :: Python :: 3.8
Classifier: Programming Language :: Python :: 3.9
Classifier: Programming Language :: Python :: 3.10
Classifier: Programming Language :: Python :: 3.11
Classifier: Programming Language :: Python :: 3.12
Classifier: Programming Language :: Python :: 3.13
Classifier: Topic :: System :: Shells
Classifier: Topic :: Education
Requires-Python: >=3.7
License-File: LICENSE
Requires-Dist: rich>=10.0.0
Requires-Dist: requests>=2.25.0
Requires-Dist: openai>=1.0.0
Provides-Extra: dev
Requires-Dist: pytest; extra == "dev"
Requires-Dist: twine; extra == "dev"
Requires-Dist: build; extra == "dev"
Provides-Extra: local-llm
Requires-Dist: llama-cpp-python; extra == "local-llm"
Requires-Dist: huggingface-hub; extra == "local-llm"
Provides-Extra: keywords
Requires-Dist: terminal; extra == "keywords"
Requires-Dist: cli; extra == "keywords"
Requires-Dist: learning; extra == "keywords"
Requires-Dist: commands; extra == "keywords"
Requires-Dist: tutorial; extra == "keywords"
Requires-Dist: zsh; extra == "keywords"
Requires-Dist: shell; extra == "keywords"
Requires-Dist: education; extra == "keywords"
Requires-Dist: real-time; extra == "keywords"
Requires-Dist: tlnr; extra == "keywords"
Requires-Dist: tldr; extra == "keywords"
Dynamic: author
Dynamic: home-page
Dynamic: license-file
Dynamic: requires-python
